evolearn/__init__.py
evolearn/feature_selection/__init__.py
evolearn/feature_selection/environment.py
evolearn/feature_selection/evaluation.py
evolearn/feature_selection/genetic_feature_selection.py
evolearn/feature_selection/initialization.py
evolearn/feature_selection/mating.py
evolearn/feature_selection/mutation.py
evolearn/feature_selection/reproduction.py
evolearn/feature_selection/selection.py
evolearn/hyperparameter_tuning/__init__.py
evolearn/hyperparameter_tuning/environment.py
evolearn/hyperparameter_tuning/evaluation.py
evolearn/hyperparameter_tuning/genes.py
evolearn/hyperparameter_tuning/genetic_hyperparameter_tuning.py
evolearn/hyperparameter_tuning/genetic_optimization.py
evolearn/hyperparameter_tuning/initialization.py
evolearn/hyperparameter_tuning/mating.py
evolearn/hyperparameter_tuning/mutation.py
evolearn/hyperparameter_tuning/reproduction.py
evolearn/hyperparameter_tuning/selection.py
evolearn/hyperparameter_tuning/experimental/__init__.py
evolearn/hyperparameter_tuning/experimental/mating.py
evolearn/hyperparameter_tuning/experimental/reproduction.py
evolearn/optimization/__init__.py
evolearn/optimization/environment.py
evolearn/optimization/evaluation.py
evolearn/optimization/genes.py
evolearn/optimization/genetic_optimization.py
evolearn/optimization/initialization.py
evolearn/optimization/mating.py
evolearn/optimization/mutation.py
evolearn/optimization/reproduction.py
evolearn/optimization/selection.py
evolearn/optimization/experimental/__init__.py
evolearn/optimization/experimental/mating.py
evolearn/optimization/experimental/reproduction.py
evolearn-1.0.8.dist-info/LICENSE.txt
evolearn-1.0.8.dist-info/METADATA
evolearn-1.0.8.dist-info/WHEEL
evolearn-1.0.8.dist-info/top_level.txt
evolearn-1.0.8.dist-info/RECORD
